{"width":513,"SubTexture":[{"frameY":-15,"y":1,"frameWidth":500,"frameHeight":500,"width":484,"height":455,"name":"penquan_5","frameX":-9,"x":1},{"width":35,"y":503,"height":46,"name":"shuibowen_2","x":278},{"width":82,"y":458,"height":92,"name":"shuibowen_1","x":1},{"width":48,"y":458,"height":55,"name":"shuibowen","x":85},{"width":24,"y":48,"height":35,"name":"shuibowen_0","x":487},{"width":62,"y":497,"height":11,"name":"shuibowen_3","x":429},{"width":36,"y":554,"height":38,"name":"1shuihua_2","x":137},{"width":37,"y":458,"height":30,"name":"1shuihua_1","x":461},{"width":46,"y":607,"height":27,"name":"2shuihua_2","x":175},{"width":36,"y":636,"height":32,"name":"2shuihua_1","x":175},{"width":30,"y":458,"height":37,"name":"3shuiwen","x":429},{"width":36,"y":594,"height":36,"name":"3shuiwen_1","x":137},{"width":19,"y":85,"height":40,"name":"1shuiwen_2","x":487},{"width":22,"y":1,"height":45,"name":"1shuiwen_1","x":487},{"width":17,"y":127,"height":33,"name":"2shuiwen_1","x":487},{"width":27,"y":549,"height":56,"name":"2shuiwen_1-2","x":184},{"width":57,"y":458,"height":30,"name":"3shuihua_1","x":326},{"width":57,"y":515,"height":33,"name":"3shuihua_2","x":85},{"width":45,"y":490,"height":36,"name":"shuye_1","x":326},{"width":38,"y":509,"height":43,"name":"shuye_2","x":144},{"width":45,"y":585,"height":34,"name":"shuye_3","x":230},{"width":42,"y":458,"height":39,"name":"shuye_4","x":385},{"width":44,"y":506,"height":41,"name":"shuye_5","x":184},{"width":45,"y":458,"height":42,"name":"hua_1","x":234},{"width":42,"y":502,"height":44,"name":"hua_2","x":234},{"width":47,"y":458,"height":49,"name":"hua_3","x":135},{"width":48,"y":458,"height":46,"name":"hua_4","x":184},{"width":43,"y":458,"height":43,"name":"hua_5","x":281},{"width":134,"y":552,"height":47,"name":"bu","x":1},{"width":45,"y":548,"height":35,"name":"shuye_6","x":230}],"height":670,"name":"penquan_5","imagePath":"penquan_5_tex.png"}