{
  "1": {"id": 1,"reword": "1:1","weight": 10,"stytle": 1,"get": 1,"index": ""},
  "2": {"id": 2,"reword": "2:1","weight": 10,"stytle": 1,"get": 1,"index": ""},
  "3": {"id": 3,"reword": "6:1","weight": 10,"stytle": 1,"get": 1,"index": ""},
  "4": {"id": 4,"reword": "7:1","weight": 10,"stytle": 1,"get": 1,"index": ""},
  "5": {"id": 5,"reword": "16:1","weight": 10,"stytle": 1,"get": 1,"index": ""},
  "6": {"id": 6,"reword": "22:1","weight": 10,"stytle": 1,"get": 1,"index": ""},
  "7": {"id": 7,"reword": "101:1","weight": 10,"stytle": 1,"get": 1,"index": ""},
  "8": {"id": 8,"reword": "107:1","weight": 10,"stytle": 1,"get": 1,"index": ""},
  "9": {"id": 9,"reword": "3:1","weight": 10,"stytle": 2,"get": 2,"index": ""},
  "10": {"id": 10,"reword": "4:1","weight": 10,"stytle": 2,"get": 2,"index": ""},
  "11": {"id": 11,"reword": "8:1","weight": 10,"stytle": 2,"get": 2,"index": ""},
  "12": {"id": 12,"reword": "9:1","weight": 10,"stytle": 2,"get": 2,"index": ""},
  "13": {"id": 13,"reword": "11:1","weight": 10,"stytle": 2,"get": 2,"index": ""},
  "14": {"id": 14,"reword": "14:1","weight": 10,"stytle": 2,"get": 2,"index": ""},
  "15": {"id": 15,"reword": "17:1","weight": 10,"stytle": 2,"get": 2,"index": ""},
  "16": {"id": 16,"reword": "18:1","weight": 10,"stytle": 2,"get": 2,"index": ""},
  "17": {"id": 17,"reword": "110:1","weight": 10,"stytle": 2,"get": 2,"index": ""},
  "18": {"id": 18,"reword": "111:1","weight": 10,"stytle": 2,"get": 2,"index": ""},
  "19": {"id": 19,"reword": "5:1","weight": 10,"stytle": 3,"get": 2,"index": ""},
  "20": {"id": 20,"reword": "10:1","weight": 10,"stytle": 3,"get": 2,"index": ""},
  "21": {"id": 21,"reword": "12:1","weight": 10,"stytle": 3,"get": 2,"index": ""},
  "22": {"id": 22,"reword": "13:1","weight": 10,"stytle": 3,"get": 2,"index": ""},
  "23": {"id": 23,"reword": "15:1","weight": 10,"stytle": 3,"get": 2,"index": ""},
  "24": {"id": 24,"reword": "19:1","weight": 10,"stytle": 3,"get": 2,"index": ""},
  "25": {"id": 25,"reword": "20:1","weight": 10,"stytle": 3,"get": 2,"index": ""},
  "26": {"id": 26,"reword": "21:1","weight": 10,"stytle": 3,"get": 2,"index": ""},
  "27": {"id": 27,"reword": "102:1","weight": 10,"stytle": 3,"get": 2,"index": ""},
  "28": {"id": 28,"reword": "103:1","weight": 10,"stytle": 3,"get": 2,"index": ""},
  "29": {"id": 29,"reword": "104:1","weight": 10,"stytle": 3,"get": 2,"index": ""},
  "30": {"id": 30,"reword": "105:1","weight": 10,"stytle": 3,"get": 2,"index": ""},
  "31": {"id": 31,"reword": "106:1","weight": 10,"stytle": 3,"get": 2,"index": ""},
  "32": {"id": 32,"reword": "108:1","weight": 10,"stytle": 3,"get": 2,"index": ""},
  "33": {"id": 33,"reword": "109:1","weight": 10,"stytle": 3,"get": 2,"index": ""},
  "34": {"id": 34,"reword": "112:1","weight": 10,"stytle": 3,"get": 2,"index": ""}
}